online_store_cu_test_kolya/__init__.py
online_store_cu_test_kolya/__main__.py
online_store_cu_test_kolya/order_management.py
online_store_cu_test_kolya/user_management.py
online_store_cu_test_kolya-0.1.1.dist-info/METADATA
online_store_cu_test_kolya-0.1.1.dist-info/WHEEL
online_store_cu_test_kolya-0.1.1.dist-info/top_level.txt
online_store_cu_test_kolya-0.1.1.dist-info/RECORD
