Metadata-Version: 2.1
Name: online_store_cu_test_kolya
Version: 0.1.1
Summary: Исполняемый пакет для управления пользователями и заказами в онлайн-магазине
Author-email: Nikolai <kolaleuhin@gmail.com>
License: MIT
Requires-Python: >=3.8
